aiogpt/__init__.py
aiogpt/auth.py
aiogpt/chat.py
aiogpt-0.0.9.dist-info/LICENSE
aiogpt-0.0.9.dist-info/METADATA
aiogpt-0.0.9.dist-info/WHEEL
aiogpt-0.0.9.dist-info/top_level.txt
aiogpt-0.0.9.dist-info/RECORD
